main.py
setup.py
bytedsp.egg-info/PKG-INFO
bytedsp.egg-info/SOURCES.txt
bytedsp.egg-info/dependency_links.txt
bytedsp.egg-info/requires.txt
bytedsp.egg-info/top_level.txt